fpga/usrp2/autoc/n_delay.v
module n_delay
  #( parameter WIDTH=8, 
     parameter DELAY=8 )
   ( input clk, 
     input wire [WIDTH-1:0] din, 
     output reg [WIDTH-1:0] dout,
     output reg outputting);
     
   reg [WIDTH-1:0] circ_buf [DELAY-1:0];   
   integer wr_ptr;
   
   wire [31:0] rd_ptr;
   initial wr_ptr <= 0;
   initial outputting <= 0;
   assign rd_ptr = (wr_ptr + 1) % DELAY;
   
   always @ (posedge clk)
     begin
       circ_buf[wr_ptr] <= din;
       dout <= circ_buf[rd_ptr];
       wr_ptr <= (wr_ptr + 1) % DELAY;
       if (rd_ptr == 0)
         outputting <= 1;
     end
   
   integer k;
   initial
     begin
       for(k = 0; k < DELAY-1; k=k+1)
         begin
           circ_buf [k] = 0;
         end
     end
     

endmodule

fpga/usrp2/autoc/n_delay_tb.v
module n_delay_tb();
   initial $dumpfile("n_delay.vcd");
   initial $dumpvars(0,n_delay_tb);

   reg clk = 0;
   always #10 clk <= ~clk;
   
   reg [17:0] in;
   
   initial in <= 18'b0;
  
  n_delay #( .WIDTH(18), .DELAY(4) ) nb
   ( .clk(clk), 
     .din(in), 
     .dout() );
     
  always @(posedge clk)
       in <= in + 2;
       
  initial
    #100000 $finish;
endmodule

fpga/usrp2/autoc/n_delay.vcd
$date
	Mon Mar 18 17:32:57 2013
$end
$version
	Icarus Verilog
$end
$timescale
	1s
$end
$scope module n_delay_tb $end
$var reg 1 ! clk $end
$var reg 18 " in [17:0] $end
$scope module nb $end
$var wire 1 # clk $end
$var wire 18 $ din [17:0] $end
$var wire 32 % rd_ptr [31:0] $end
$var reg 18 & dout [17:0] $end
$var integer 32 ' k [31:0] $end
$var reg 1 ( outputting $end
$var integer 32 ) wr_ptr [31:0] $end
$upscope $end
$upscope $end
$enddefinitions $end
#0
$dumpvars
b0 )
0(
b11 '
bx &
b1 %
b0 $
0#
b0 "
0!
$end
#10
b10 %
b1 )
b0 &
b10 "
b10 $
1!
1#
#20
0!
0#
#30
b11 %
b100 "
b100 $
b10 )
1!
1#
#40
0!
0#
#50
b0 %
b11 )
bx &
b110 "
b110 $
1!
1#
#60
0!
0#
#70
b1 %
b1000 "
b1000 $
1(
b0 )
b0 &
1!
1#
#80
0!
0#
#90
b10 %
b1 )
b10 &
b1010 "
b1010 $
1!
1#
#100
0!
0#
#110
b11 %
b1100 "
b1100 $
b10 )
b100 &
1!
1#
#120
0!
0#
#130
b0 %
b11 )
b110 &
b1110 "
b1110 $
1!
1#
#140
0!
0#
#150
b1 %
b10000 "
b10000 $
b0 )
b1000 &
1!
1#
#160
0!
0#
#170
b10 %
b1 )
b1010 &
b10010 "
b10010 $
1!
1#
#180
0!
0#
#190
b11 %
b10100 "
b10100 $
b10 )
b1100 &
1!
1#
#200
0!
0#
#210
b0 %
b11 )
b1110 &
b10110 "
b10110 $
1!
1#
#220
0!
0#
#230
b1 %
b11000 "
b11000 $
b0 )
b10000 &
1!
1#
#240
0!
0#
#250
b10 %
b1 )
b10010 &
b11010 "
b11010 $
1!
1#
#260
0!
0#
#270
b11 %
b11100 "
b11100 $
b10 )
b10100 &
1!
1#
#280
0!
0#
#290
b0 %
b11 )
b10110 &
b11110 "
b11110 $
1!
1#
#300
0!
0#
#310
b1 %
b100000 "
b100000 $
b0 )
b11000 &
1!
1#
#320
0!
0#
#330
b10 %
b1 )
b11010 &
b100010 "
b100010 $
1!
1#
#340
0!
0#
#350
b11 %
b100100 "
b100100 $
b10 )
b11100 &
1!
1#
#360
0!
0#
#370
b0 %
b11 )
b11110 &
b100110 "
b100110 $
1!
1#
#380
0!
0#
#390
b1 %
b101000 "
b101000 $
b0 )
b100000 &
1!
1#
#400
0!
0#
#410
b10 %
b1 )
b100010 &
b101010 "
b101010 $
1!
1#
#420
0!
0#
#430
b11 %
b101100 "
b101100 $
b10 )
b100100 &
1!
1#
#440
0!
0#
#450
b0 %
b11 )
b100110 &
b101110 "
b101110 $
1!
1#
#460
0!
0#
#470
b1 %
b110000 "
b110000 $
b0 )
b101000 &
1!
1#
#480
0!
0#
#490
b10 %
b1 )
b101010 &
b110010 "
b110010 $
1!
1#
#500
0!
0#
#510
b11 %
b110100 "
b110100 $
b10 )
b101100 &
1!
1#
#520
0!
0#
#530
b0 %
b11 )
b101110 &
b110110 "
b110110 $
1!
1#
#540
0!
0#
#550
b1 %
b111000 "
b111000 $
b0 )
b110000 &
1!
1#
#560
0!
0#
#570
b10 %
b1 )
b110010 &
b111010 "
b111010 $
1!
1#
#580
0!
0#
#590
b11 %
b111100 "
b111100 $
b10 )
b110100 &
1!
1#
#600
0!
0#
#610
b0 %
b11 )
b110110 &
b111110 "
b111110 $
1!
1#
#620
0!
0#
#630
b1 %
b1000000 "
b1000000 $
b0 )
b111000 &
1!
1#
#640
0!
0#
#650
b10 %
b1 )
b111010 &
b1000010 "
b1000010 $
1!
1#
#660
0!
0#
#670
b11 %
b1000100 "
b1000100 $
b10 )
b111100 &
1!
1#
#680
0!
0#
#690
b0 %
b11 )
b111110 &
b1000110 "
b1000110 $
1!
1#
#700
0!
0#
#710
b1 %
b1001000 "
b1001000 $
b0 )
b1000000 &
1!
1#
#720
0!
0#
#730
b10 %
b1 )
b1000010 &
b1001010 "
b1001010 $
1!
1#
#740
0!
0#
#750
b11 %
b1001100 "
b1001100 $
b10 )
b1000100 &
1!
1#
#760
0!
0#
#770
b0 %
b11 )
b1000110 &
b1001110 "
b1001110 $
1!
1#
#780
0!
0#
#790
b1 %
b1010000 "
b1010000 $
b0 )
b1001000 &
1!
1#
#800
0!
0#
#810
b10 %
b1 )
b1001010 &
b1010010 "
b1010010 $
1!
1#
#820
0!
0#
#830
b11 %
b1010100 "
b1010100 $
b10 )
b1001100 &
1!
1#
#840
0!
0#
#850
b0 %
b11 )
b1001110 &
b1010110 "
b1010110 $
1!
1#
#860
0!
0#
#870
b1 %
b1011000 "
b1011000 $
b0 )
b1010000 &
1!
1#
#880
0!
0#
#890
b10 %
b1 )
b1010010 &
b1011010 "
b1011010 $
1!
1#
#900
0!
0#
#910
b11 %
b1011100 "
b1011100 $
b10 )
b1010100 &
1!
1#
#920
0!
0#
#930
b0 %
b11 )
b1010110 &
b1011110 "
b1011110 $
1!
1#
#940
0!
0#
#950
b1 %
b1100000 "
b1100000 $
b0 )
b1011000 &
1!
1#
#960
0!
0#
#970
b10 %
b1 )
b1011010 &
b1100010 "
b1100010 $
1!
1#
#980
0!
0#
#990
b11 %
b1100100 "
b1100100 $
b10 )
b1011100 &
1!
1#
#1000
0!
0#
#1010
b0 %
b11 )
b1011110 &
b1100110 "
b1100110 $
1!
1#
#1020
0!
0#
#1030
b1 %
b1101000 "
b1101000 $
b0 )
b1100000 &
1!
1#
#1040
0!
0#
#1050
b10 %
b1 )
b1100010 &
b1101010 "
b1101010 $
1!
1#
#1060
0!
0#
#1070
b11 %
b1101100 "
b1101100 $
b10 )
b1100100 &
1!
1#
#1080
0!
0#
#1090
b0 %
b11 )
b1100110 &
b1101110 "
b1101110 $
1!
1#
#1100
0!
0#
#1110
b1 %
b1110000 "
b1110000 $
b0 )
b1101000 &
1!
1#
#1120
0!
0#
#1130
b10 %
b1 )
b1101010 &
b1110010 "
b1110010 $
1!
1#
#1140
0!
0#
#1150
b11 %
b1110100 "
b1110100 $
b10 )
b1101100 &
1!
1#
#1160
0!
0#
#1170
b0 %
b11 )
b1101110 &
b1110110 "
b1110110 $
1!
1#
#1180
0!
0#
#1190
b1 %
b1111000 "
b1111000 $
b0 )
b1110000 &
1!
1#
#1200
0!
0#
#1210
b10 %
b1 )
b1110010 &
b1111010 "
b1111010 $
1!
1#
#1220
0!
0#
#1230
b11 %
b1111100 "
b1111100 $
b10 )
b1110100 &
1!
1#
#1240
0!
0#
#1250
b0 %
b11 )
b1110110 &
b1111110 "
b1111110 $
1!
1#
#1260
0!
0#
#1270
b1 %
b10000000 "
b10000000 $
b0 )
b1111000 &
1!
1#
#1280
0!
0#
#1290
b10 %
b1 )
b1111010 &
b10000010 "
b10000010 $
1!
1#
#1300
0!
0#
#1310
b11 %
b10000100 "
b10000100 $
b10 )
b1111100 &
1!
1#
#1320
0!
0#
#1330
b0 %
b11 )
b1111110 &
b10000110 "
b10000110 $
1!
1#
#1340
0!
0#
#1350
b1 %
b10001000 "
b10001000 $
b0 )
b10000000 &
1!
1#
#1360
0!
0#
#1370
b10 %
b1 )
b10000010 &
b10001010 "
b10001010 $
1!
1#
#1380
0!
0#
#1390
b11 %
b10001100 "
b10001100 $
b10 )
b10000100 &
1!
1#
#1400
0!
0#
#1410
b0 %
b11 )
b10000110 &
b10001110 "
b10001110 $
1!
1#
#1420
0!
0#
#1430
b1 %
b10010000 "
b10010000 $
b0 )
b10001000 &
1!
1#
#1440
0!
0#
#1450
b10 %
b1 )
b10001010 &
b10010010 "
b10010010 $
1!
1#
#1460
0!
0#
#1470
b11 %
b10010100 "
b10010100 $
b10 )
b10001100 &
1!
1#
#1480
0!
0#
#1490
b0 %
b11 )
b10001110 &
b10010110 "
b10010110 $
1!
1#
#1500
0!
0#
#1510
b1 %
b10011000 "
b10011000 $
b0 )
b10010000 &
1!
1#
#1520
0!
0#
#1530
b10 %
b1 )
b10010010 &
b10011010 "
b10011010 $
1!
1#
#1540
0!
0#
#1550
b11 %
b10011100 "
b10011100 $
b10 )
b10010100 &
1!
1#
#1560
0!
0#
#1570
b0 %
b11 )
b10010110 &
b10011110 "
b10011110 $
1!
1#
#1580
0!
0#
#1590
b1 %
b10100000 "
b10100000 $
b0 )
b10011000 &
1!
1#
#1600
0!
0#
#1610
b10 %
b1 )
b10011010 &
b10100010 "
b10100010 $
1!
1#
#1620
0!
0#
#1630
b11 %
b10100100 "
b10100100 $
b10 )
b10011100 &
1!
1#
#1640
0!
0#
#1650
b0 %
b11 )
b10011110 &
b10100110 "
b10100110 $
1!
1#
#1660
0!
0#
#1670
b1 %
b10101000 "
b10101000 $
b0 )
b10100000 &
1!
1#
#1680
0!
0#
#1690
b10 %
b1 )
b10100010 &
b10101010 "
b10101010 $
1!
1#
#1700
0!
0#
#1710
b11 %
b10101100 "
b10101100 $
b10 )
b10100100 &
1!
1#
#1720
0!
0#
#1730
b0 %
b11 )
b10100110 &
b10101110 "
b10101110 $
1!
1#
#1740
0!
0#
#1750
b1 %
b10110000 "
b10110000 $
b0 )
b10101000 &
1!
1#
#1760
0!
0#
#1770
b10 %
b1 )
b10101010 &
b10110010 "
b10110010 $
1!
1#
#1780
0!
0#
#1790
b11 %
b10110100 "
b10110100 $
b10 )
b10101100 &
1!
1#
#1800
0!
0#
#1810
b0 %
b11 )
b10101110 &
b10110110 "
b10110110 $
1!
1#
#1820
0!
0#
#1830
b1 %
b10111000 "
b10111000 $
b0 )
b10110000 &
1!
1#
#1840
0!
0#
#1850
b10 %
b1 )
b10110010 &
b10111010 "
b10111010 $
1!
1#
#1860
0!
0#
#1870
b11 %
b10111100 "
b10111100 $
b10 )
b10110100 &
1!
1#
#1880
0!
0#
#1890
b0 %
b11 )
b10110110 &
b10111110 "
b10111110 $
1!
1#
#1900
0!
0#
#1910
b1 %
b11000000 "
b11000000 $
b0 )
b10111000 &
1!
1#
#1920
0!
0#
#1930
b10 %
b1 )
b10111010 &
b11000010 "
b11000010 $
1!
1#
#1940
0!
0#
#1950
b11 %
b11000100 "
b11000100 $
b10 )
b10111100 &
1!
1#
#1960
0!
0#
#1970
b0 %
b11 )
b10111110 &
b11000110 "
b11000110 $
1!
1#
#1980
0!
0#
#1990
b1 %
b11001000 "
b11001000 $
b0 )
b11000000 &
1!
1#
#2000
0!
0#
#2010
b10 %
b1 )
b11000010 &
b11001010 "
b11001010 $
1!
1#
#2020
0!
0#
#2030
b11 %
b11001100 "
b11001100 $
b10 )
b11000100 &
1!
1#
#2040
0!
0#
#2050
b0 %
b11 )
b11000110 &
b11001110 "
b11001110 $
1!
1#
#2060
0!
0#
#2070
b1 %
b11010000 "
b11010000 $
b0 )
b11001000 &
1!
1#
#2080
0!
0#
#2090
b10 %
b1 )
b11001010 &
b11010010 "
b11010010 $
1!
1#
#2100
0!
0#
#2110
b11 %
b11010100 "
b11010100 $
b10 )
b11001100 &
1!
1#
#2120
0!
0#
#2130
b0 %
b11 )
b11001110 &
b11010110 "
b11010110 $
1!
1#
#2140
0!
0#
#2150
b1 %
b11011000 "
b11011000 $
b0 )
b11010000 &
1!
1#
#2160
0!
0#
#2170
b10 %
b1 )
b11010010 &
b11011010 "
b11011010 $
1!
1#
#2180
0!
0#
#2190
b11 %
b11011100 "
b11011100 $
b10 )
b11010100 &
1!
1#
#2200
0!
0#
#2210
b0 %
b11 )
b11010110 &
b11011110 "
b11011110 $
1!
1#
#2220
0!
0#
#2230
b1 %
b11100000 "
b11100000 $
b0 )
b11011000 &
1!
1#
#2240
0!
0#
#2250
b10 %
b1 )
b11011010 &
b11100010 "
b11100010 $
1!
1#
#2260
0!
0#
#2270
b11 %
b11100100 "
b11100100 $
b10 )
b11011100 &
1!
1#
#2280
0!
0#
#2290
b0 %
b11 )
b11011110 &
b11100110 "
b11100110 $
1!
1#
#2300
0!
0#
#2310
b1 %
b11101000 "
b11101000 $
b0 )
b11100000 &
1!
1#
#2320
0!
0#
#2330
b10 %
b1 )
b11100010 &
b11101010 "
b11101010 $
1!
1#
#2340
0!
0#
#2350
b11 %
b11101100 "
b11101100 $
b10 )
b11100100 &
1!
1#
#2360
0!
0#
#2370
b0 %
b11 )
b11100110 &
b11101110 "
b11101110 $
1!
1#
#2380
0!
0#
#2390
b1 %
b11110000 "
b11110000 $
b0 )
b11101000 &
1!
1#
#2400
0!
0#
#2410
b10 %
b1 )
b11101010 &
b11110010 "
b11110010 $
1!
1#
#2420
0!
0#
#2430
b11 %
b11110100 "
b11110100 $
b10 )
b11101100 &
1!
1#
#2440
0!
0#
#2450
b0 %
b11 )
b11101110 &
b11110110 "
b11110110 $
1!
1#
#2460
0!
0#
#2470
b1 %
b11111000 "
b11111000 $
b0 )
b11110000 &
1!
1#
#2480
0!
0#
#2490
b10 %
b1 )
b11110010 &
b11111010 "
b11111010 $
1!
1#
#2500
0!
0#
#2510
b11 %
b11111100 "
b11111100 $
b10 )
b11110100 &
1!
1#
#2520
0!
0#
#2530
b0 %
b11 )
b11110110 &
b11111110 "
b11111110 $
1!
1#
#2540
0!
0#
#2550
b1 %
b100000000 "
b100000000 $
b0 )
b11111000 &
1!
1#
#2560
0!
0#
#2570
b10 %
b1 )
b11111010 &
b100000010 "
b100000010 $
1!
1#
#2580
0!
0#
#2590
b11 %
b100000100 "
b100000100 $
b10 )
b11111100 &
1!
1#
#2600
0!
0#
#2610
b0 %
b11 )
b11111110 &
b100000110 "
b100000110 $
1!
1#
#2620
0!
0#
#2630
b1 %
b100001000 "
b100001000 $
b0 )
b100000000 &
1!
1#
#2640
0!
0#
#2650
b10 %
b1 )
b100000010 &
b100001010 "
b100001010 $
1!
1#
#2660
0!
0#
#2670
b11 %
b100001100 "
b100001100 $
b10 )
b100000100 &
1!
1#
#2680
0!
0#
#2690
b0 %
b11 )
b100000110 &
b100001110 "
b100001110 $
1!
1#
#2700
0!
0#
#2710
b1 %
b100010000 "
b100010000 $
b0 )
b100001000 &
1!
1#
#2720
0!
0#
#2730
b10 %
b1 )
b100001010 &
b100010010 "
b100010010 $
1!
1#
#2740
0!
0#
#2750
b11 %
b100010100 "
b100010100 $
b10 )
b100001100 &
1!
1#
#2760
0!
0#
#2770
b0 %
b11 )
b100001110 &
b100010110 "
b100010110 $
1!
1#
#2780
0!
0#
#2790
b1 %
b100011000 "
b100011000 $
b0 )
b100010000 &
1!
1#
#2800
0!
0#
#2810
b10 %
b1 )
b100010010 &
b100011010 "
b100011010 $
1!
1#
#2820
0!
0#
#2830
b11 %
b100011100 "
b100011100 $
b10 )
b100010100 &
1!
1#
#2840
0!
0#
#2850
b0 %
b11 )
b100010110 &
b100011110 "
b100011110 $
1!
1#
#2860
0!
0#
#2870
b1 %
b100100000 "
b100100000 $
b0 )
b100011000 &
1!
1#
#2880
0!
0#
#2890
b10 %
b1 )
b100011010 &
b100100010 "
b100100010 $
1!
1#
#2900
0!
0#
#2910
b11 %
b100100100 "
b100100100 $
b10 )
b100011100 &
1!
1#
#2920
0!
0#
#2930
b0 %
b11 )
b100011110 &
b100100110 "
b100100110 $
1!
1#
#2940
0!
0#
#2950
b1 %
b100101000 "
b100101000 $
b0 )
b100100000 &
1!
1#
#2960
0!
0#
#2970
b10 %
b1 )
b100100010 &
b100101010 "
b100101010 $
1!
1#
#2980
0!
0#
#2990
b11 %
b100101100 "
b100101100 $
b10 )
b100100100 &
1!
1#
#3000
0!
0#
#3010
b0 %
b11 )
b100100110 &
b100101110 "
b100101110 $
1!
1#
#3020
0!
0#
#3030
b1 %
b100110000 "
b100110000 $
b0 )
b100101000 &
1!
1#
#3040
0!
0#
#3050
b10 %
b1 )
b100101010 &
b100110010 "
b100110010 $
1!
1#
#3060
0!
0#
#3070
b11 %
b100110100 "
b100110100 $
b10 )
b100101100 &
1!
1#
#3080
0!
0#
#3090
b0 %
b11 )
b100101110 &
b100110110 "
b100110110 $
1!
1#
#3100
0!
0#
#3110
b1 %
b100111000 "
b100111000 $
b0 )
b100110000 &
1!
1#
#3120
0!
0#
#3130
b10 %
b1 )
b100110010 &
b100111010 "
b100111010 $
1!
1#
#3140
0!
0#
#3150
b11 %
b100111100 "
b100111100 $
b10 )
b100110100 &
1!
1#
#3160
0!
0#
#3170
b0 %
b11 )
b100110110 &
b100111110 "
b100111110 $
1!
1#
#3180
0!
0#
#3190
b1 %
b101000000 "
b101000000 $
b0 )
b100111000 &
1!
1#
#3200
0!
0#
#3210
b10 %
b1 )
b100111010 &
b101000010 "
b101000010 $
1!
1#
#3220
0!
0#
#3230
b11 %
b101000100 "
b101000100 $
b10 )
b100111100 &
1!
1#
#3240
0!
0#
#3250
b0 %
b11 )
b100111110 &
b101000110 "
b101000110 $
1!
1#
#3260
0!
0#
#3270
b1 %
b101001000 "
b101001000 $
b0 )
b101000000 &
1!
1#
#3280
0!
0#
#3290
b10 %
b1 )
b101000010 &
b101001010 "
b101001010 $
1!
1#
#3300
0!
0#
#3310
b11 %
b101001100 "
b101001100 $
b10 )
b101000100 &
1!
1#
#3320
0!
0#
#3330
b0 %
b11 )
b101000110 &
b101001110 "
b101001110 $
1!
1#
#3340
0!
0#
#3350
b1 %
b101010000 "
b101010000 $
b0 )
b101001000 &
1!
1#
#3360
0!
0#
#3370
b10 %
b1 )
b101001010 &
b101010010 "
b101010010 $
1!
1#
#3380
0!
0#
#3390
b11 %
b101010100 "
b101010100 $
b10 )
b101001100 &
1!
1#
#3400
0!
0#
#3410
b0 %
b11 )
b101001110 &
b101010110 "
b101010110 $
1!
1#
#3420
0!
0#
#3430
b1 %
b101011000 "
b101011000 $
b0 )
b101010000 &
1!
1#
#3440
0!
0#
#3450
b10 %
b1 )
b101010010 &
b101011010 "
b101011010 $
1!
1#
#3460
0!
0#
#3470
b11 %
b101011100 "
b101011100 $
b10 )
b101010100 &
1!
1#
#3480
0!
0#
#3490
b0 %
b11 )
b101010110 &
b101011110 "
b101011110 $
1!
1#
#3500
0!
0#
#3510
b1 %
b101100000 "
b101100000 $
b0 )
b101011000 &
1!
1#
#3520
0!
0#
#3530
b10 %
b1 )
b101011010 &
b101100010 "
b101100010 $
1!
1#
#3540
0!
0#
#3550
b11 %
b101100100 "
b101100100 $
b10 )
b101011100 &
1!
1#
#3560
0!
0#
#3570
b0 %
b11 )
b101011110 &
b101100110 "
b101100110 $
1!
1#
#3580
0!
0#
#3590
b1 %
b101101000 "
b101101000 $
b0 )
b101100000 &
1!
1#
#3600
0!
0#
#3610
b10 %
b1 )
b101100010 &
b101101010 "
b101101010 $
1!
1#
#3620
0!
0#
#3630
b11 %
b101101100 "
b101101100 $
b10 )
b101100100 &
1!
1#
#3640
0!
0#
#3650
b0 %
b11 )
b101100110 &
b101101110 "
b101101110 $
1!
1#
#3660
0!
0#
#3670
b1 %
b101110000 "
b101110000 $
b0 )
b101101000 &
1!
1#
#3680
0!
0#
#3690
b10 %
b1 )
b101101010 &
b101110010 "
b101110010 $
1!
1#
#3700
0!
0#
#3710
b11 %
b101110100 "
b101110100 $
b10 )
b101101100 &
1!
1#
#3720
0!
0#
#3730
b0 %
b11 )
b101101110 &
b101110110 "
b101110110 $
1!
1#
#3740
0!
0#
#3750
b1 %
b101111000 "
b101111000 $
b0 )
b101110000 &
1!
1#
#3760
0!
0#
#3770
b10 %
b1 )
b101110010 &
b101111010 "
b101111010 $
1!
1#
#3780
0!
0#
#3790
b11 %
b101111100 "
b101111100 $
b10 )
b101110100 &
1!
1#
#3800
0!
0#
#3810
b0 %
b11 )
b101110110 &
b101111110 "
b101111110 $
1!
1#
#3820
0!
0#
#3830
b1 %
b110000000 "
b110000000 $
b0 )
b101111000 &
1!
1#
#3840
0!
0#
#3850
b10 %
b1 )
b101111010 &
b110000010 "
b110000010 $
1!
1#
#3860
0!
0#
#3870
b11 %
b110000100 "
b110000100 $
b10 )
b101111100 &
1!
1#
#3880
0!
0#
#3890
b0 %
b11 )
b101111110 &
b110000110 "
b110000110 $
1!
1#
#3900
0!
0#
#3910
b1 %
b110001000 "
b110001000 $
b0 )
b110000000 &
1!
1#
#3920
0!
0#
#3930
b10 %
b1 )
b110000010 &
b110001010 "
b110001010 $
1!
1#
#3940
0!
0#
#3950
b11 %
b110001100 "
b110001100 $
b10 )
b110000100 &
1!
1#
#3960
0!
0#
#3970
b0 %
b11 )
b110000110 &
b110001110 "
b110001110 $
1!
1#
#3980
0!
0#
#3990
b1 %
b110010000 "
b110010000 $
b0 )
b110001000 &
1!
1#
#4000
0!
0#
#4010
b10 %
b1 )
b110001010 &
b110010010 "
b110010010 $
1!
1#
#4020
0!
0#
#4030
b11 %
b110010100 "
b110010100 $
b10 )
b110001100 &
1!
1#
#4040
0!
0#
#4050
b0 %
b11 )
b110001110 &
b110010110 "
b110010110 $
1!
1#
#4060
0!
0#
#4070
b1 %
b110011000 "
b110011000 $
b0 )
b110010000 &
1!
1#
#4080
0!
0#
#4090
b10 %
b1 )
b110010010 &
b110011010 "
b110011010 $
1!
1#
#4100
0!
0#
#4110
b11 %
b110011100 "
b110011100 $
b10 )
b110010100 &
1!
1#
#4120
0!
0#
#4130
b0 %
b11 )
b110010110 &
b110011110 "
b110011110 $
1!
1#
#4140
0!
0#
#4150
b1 %
b110100000 "
b110100000 $
b0 )
b110011000 &
1!
1#
#4160
0!
0#
#4170
b10 %
b1 )
b110011010 &
b110100010 "
b110100010 $
1!
1#
#4180
0!
0#
#4190
b11 %
b110100100 "
b110100100 $
b10 )
b110011100 &
1!
1#
#4200
0!
0#
#4210
b0 %
b11 )
b110011110 &
b110100110 "
b110100110 $
1!
1#
#4220
0!
0#
#4230
b1 %
b110101000 "
b110101000 $
b0 )
b110100000 &
1!
1#
#4240
0!
0#
#4250
b10 %
b1 )
b110100010 &
b110101010 "
b110101010 $
1!
1#
#4260
0!
0#
#4270
b11 %
b110101100 "
b110101100 $
b10 )
b110100100 &
1!
1#
#4280
0!
0#
#4290
b0 %
b11 )
b110100110 &
b110101110 "
b110101110 $
1!
1#
#4300
0!
0#
#4310
b1 %
b110110000 "
b110110000 $
b0 )
b110101000 &
1!
1#
#4320
0!
0#
#4330
b10 %
b1 )
b110101010 &
b110110010 "
b110110010 $
1!
1#
#4340
0!
0#
#4350
b11 %
b110110100 "
b110110100 $
b10 )
b110101100 &
1!
1#
#4360
0!
0#
#4370
b0 %
b11 )
b110101110 &
b110110110 "
b110110110 $
1!
1#
#4380
0!
0#
#4390
b1 %
b110111000 "
b110111000 $
b0 )
b110110000 &
1!
1#
#4400
0!
0#
#4410
b10 %
b1 )
b110110010 &
b110111010 "
b110111010 $
1!
1#
#4420
0!
0#
#4430
b11 %
b110111100 "
b110111100 $
b10 )
b110110100 &
1!
1#
#4440
0!
0#
#4450
b0 %
b11 )
b110110110 &
b110111110 "
b110111110 $
1!
1#
#4460
0!
0#
#4470
b1 %
b111000000 "
b111000000 $
b0 )
b110111000 &
1!
1#
#4480
0!
0#
#4490
b10 %
b1 )
b110111010 &
b111000010 "
b111000010 $
1!
1#
#4500
0!
0#
#4510
b11 %
b111000100 "
b111000100 $
b10 )
b110111100 &
1!
1#
#4520
0!
0#
#4530
b0 %
b11 )
b110111110 &
b111000110 "
b111000110 $
1!
1#
#4540
0!
0#
#4550
b1 %
b111001000 "
b111001000 $
b0 )
b111000000 &
1!
1#
#4560
0!
0#
#4570
b10 %
b1 )
b111000010 &
b111001010 "
b111001010 $
1!
1#
#4580
0!
0#
#4590
b11 %
b111001100 "
b111001100 $
b10 )
b111000100 &
1!
1#
#4600
0!
0#
#4610
b0 %
b11 )
b111000110 &
b111001110 "
b111001110 $
1!
1#
#4620
0!
0#
#4630
b1 %
b111010000 "
b111010000 $
b0 )
b111001000 &
1!
1#
#4640
0!
0#
#4650
b10 %
b1 )
b111001010 &
b111010010 "
b111010010 $
1!
1#
#4660
0!
0#
#4670
b11 %
b111010100 "
b111010100 $
b10 )
b111001100 &
1!
1#
#4680
0!
0#
#4690
b0 %
b11 )
b111001110 &
b111010110 "
b111010110 $
1!
1#
#4700
0!
0#
#4710
b1 %
b111011000 "
b111011000 $
b0 )
b111010000 &
1!
1#
#4720
0!
0#
#4730
b10 %
b1 )
b111010010 &
b111011010 "
b111011010 $
1!
1#
#4740
0!
0#
#4750
b11 %
b111011100 "
b111011100 $
b10 )
b111010100 &
1!
1#
#4760
0!
0#
#4770
b0 %
b11 )
b111010110 &
b111011110 "
b111011110 $
1!
1#
#4780
0!
0#
#4790
b1 %
b111100000 "
b111100000 $
b0 )
b111011000 &
1!
1#
#4800
0!
0#
#4810
b10 %
b1 )
b111011010 &
b111100010 "
b111100010 $
1!
1#
#4820
0!
0#
#4830
b11 %
b111100100 "
b111100100 $
b10 )
b111011100 &
1!
1#
#4840
0!
0#
#4850
b0 %
b11 )
b111011110 &
b111100110 "
b111100110 $
1!
1#
#4860
0!
0#
#4870
b1 %
b111101000 "
b111101000 $
b0 )
b111100000 &
1!
1#
#4880
0!
0#
#4890
b10 %
b1 )
b111100010 &
b111101010 "
b111101010 $
1!
1#
#4900
0!
0#
#4910
b11 %
b111101100 "
b111101100 $
b10 )
b111100100 &
1!
1#
#4920
0!
0#
#4930
b0 %
b11 )
b111100110 &
b111101110 "
b111101110 $
1!
1#
#4940
0!
0#
#4950
b1 %
b111110000 "
b111110000 $
b0 )
b111101000 &
1!
1#
#4960
0!
0#
#4970
b10 %
b1 )
b111101010 &
b111110010 "
b111110010 $
1!
1#
#4980
0!
0#
#4990
b11 %
b111110100 "
b111110100 $
b10 )
b111101100 &
1!
1#
#5000
0!
0#
#5010
b0 %
b11 )
b111101110 &
b111110110 "
b111110110 $
1!
1#
#5020
0!
0#
#5030
b1 %
b111111000 "
b111111000 $
b0 )
b111110000 &
1!
1#
#5040
0!
0#
#5050
b10 %
b1 )
b111110010 &
b111111010 "
b111111010 $
1!
1#
#5060
0!
0#
#5070
b11 %
b111111100 "
b111111100 $
b10 )
b111110100 &
1!
1#
#5080
0!
0#
#5090
b0 %
b11 )
b111110110 &
b111111110 "
b111111110 $
1!
1#
#5100
0!
0#
#5110
b1 %
b1000000000 "
b1000000000 $
b0 )
b111111000 &
1!
1#
#5120
0!
0#
#5130
b10 %
b1 )
b111111010 &
b1000000010 "
b1000000010 $
1!
1#
#5140
0!
0#
#5150
b11 %
b1000000100 "
b1000000100 $
b10 )
b111111100 &
1!
1#
#5160
0!
0#
#5170
b0 %
b11 )
b111111110 &
b1000000110 "
b1000000110 $
1!
1#
#5180
0!
0#
#5190
b1 %
b1000001000 "
b1000001000 $
b0 )
b1000000000 &
1!
1#
#5200
0!
0#
#5210
b10 %
b1 )
b1000000010 &
b1000001010 "
b1000001010 $
1!
1#
#5220
0!
0#
#5230
b11 %
b1000001100 "
b1000001100 $
b10 )
b1000000100 &
1!
1#
#5240
0!
0#
#5250
b0 %
b11 )
b1000000110 &
b1000001110 "
b1000001110 $
1!
1#
#5260
0!
0#
#5270
b1 %
b1000010000 "
b1000010000 $
b0 )
b1000001000 &
1!
1#
#5280
0!
0#
#5290
b10 %
b1 )
b1000001010 &
b1000010010 "
b1000010010 $
1!
1#
#5300
0!
0#
#5310
b11 %
b1000010100 "
b1000010100 $
b10 )
b1000001100 &
1!
1#
#5320
0!
0#
#5330
b0 %
b11 )
b1000001110 &
b1000010110 "
b1000010110 $
1!
1#
#5340
0!
0#
#5350
b1 %
b1000011000 "
b1000011000 $
b0 )
b1000010000 &
1!
1#
#5360
0!
0#
#5370
b10 %
b1 )
b1000010010 &
b1000011010 "
b1000011010 $
1!
1#
#5380
0!
0#
#5390
b11 %
b1000011100 "
b1000011100 $
b10 )
b1000010100 &
1!
1#
#5400
0!
0#
#5410
b0 %
b11 )
b1000010110 &
b1000011110 "
b1000011110 $
1!
1#
#5420
0!
0#
#5430
b1 %
b1000100000 "
b1000100000 $
b0 )
b1000011000 &
1!
1#
#5440
0!
0#
#5450
b10 %
b1 )
b1000011010 &
b1000100010 "
b1000100010 $
1!
1#
#5460
0!
0#
#5470
b11 %
b1000100100 "
b1000100100 $
b10 )
b1000011100 &
1!
1#
#5480
0!
0#
#5490
b0 %
b11 )
b1000011110 &
b1000100110 "
b1000100110 $
1!
1#
#5500
0!
0#
#5510
b1 %
b1000101000 "
b1000101000 $
b0 )
b1000100000 &
1!
1#
#5520
0!
0#
#5530
b10 %
b1 )
b1000100010 &
b1000101010 "
b1000101010 $
1!
1#
#5540
0!
0#
#5550
b11 %
b1000101100 "
b1000101100 $
b10 )
b1000100100 &
1!
1#
#5560
0!
0#
